isdn/__init__.py
isdn/client.py
isdn/command.py
isdn/model.py
isdn/parser.py
isdn-2.0.0.dist-info/LICENSE
isdn-2.0.0.dist-info/METADATA
isdn-2.0.0.dist-info/WHEEL
isdn-2.0.0.dist-info/entry_points.txt
isdn-2.0.0.dist-info/RECORD
