Metadata-Version: 2.1
Name: isdn
Version: 2.0.0
Summary: Library for ISDN (International Standard Dojin Numbering)
Home-page: https://github.com/Babibubebon/isdn-python
License: MIT
Keywords: book,doujinshi,identifier
Author: Babibubebon
Author-email: babibubebon@babibubebo.org
Requires-Python: >=3.10,<4.0
Classifier: Environment :: Console
Classifier: License :: OSI Approved :: MIT License
Classifier: Programming Language :: Python
Classifier: Programming Language :: Python :: 3
Classifier: Programming Language :: Python :: 3.10
Classifier: Programming Language :: Python :: 3.11
Classifier: Topic :: Software Development :: Libraries :: Python Modules
Requires-Dist: click (>=8.1.3,<9.0.0)
Requires-Dist: pydantic-xml[lxml] (>=2.18.0,<3.0.0)
Requires-Dist: requests (>=2.28.2,<3.0.0)
Project-URL: Repository, https://github.com/Babibubebon/isdn-python
